llm_exceptions/__init__.py
llm_exceptions/llm_exceptions.py
llm_exceptions-0.0.6.dist-info/LICENSE
llm_exceptions-0.0.6.dist-info/METADATA
llm_exceptions-0.0.6.dist-info/WHEEL
llm_exceptions-0.0.6.dist-info/entry_points.txt
llm_exceptions-0.0.6.dist-info/top_level.txt
llm_exceptions-0.0.6.dist-info/RECORD
